lepo/__init__.py
lepo/api_info.py
lepo/codegen.py
lepo/decoders.py
lepo/decorators.py
lepo/excs.py
lepo/handlers.py
lepo/parameter_utils.py
lepo/path_view.py
lepo/router.py
lepo/utils.py
lepo/validate.py
lepo/apidef/__init__.py
lepo/apidef/doc.py
lepo/apidef/path.py
lepo/apidef/version.py
lepo/apidef/operation/__init__.py
lepo/apidef/operation/base.py
lepo/apidef/operation/openapi.py
lepo/apidef/operation/swagger.py
lepo/apidef/parameter/__init__.py
lepo/apidef/parameter/base.py
lepo/apidef/parameter/openapi.py
lepo/apidef/parameter/swagger.py
lepo/apidef/parameter/utils.py
lepo_doc/__init__.py
lepo_doc/urls.py
lepo_doc/views.py
lepo_doc/static/lepo_doc/swagger-ui/swagger-ui-bundle.js
lepo_doc/static/lepo_doc/swagger-ui/swagger-ui.css
lepo_doc/templates/lepo_doc/swagger-ui.html
lepo-0.3.0.dist-info/LICENSE
lepo-0.3.0.dist-info/METADATA
lepo-0.3.0.dist-info/WHEEL
lepo-0.3.0.dist-info/top_level.txt
lepo-0.3.0.dist-info/RECORD
