Metadata-Version: 2.1
Name: lepo
Version: 0.3.0
Summary: UNKNOWN
Home-page: https://github.com/akx/lepo
Author: Aarni Koskela
Author-email: akx@iki.fi
Maintainer: Aarni Koskela
Maintainer-email: akx@iki.fi
License: MIT
Platform: UNKNOWN
Requires-Dist: Django (>=2.2)
Requires-Dist: iso8601
Requires-Dist: jsonschema (~=3.2)
Requires-Dist: marshmallow (~=3.0)
